locan/__init__.py
locan/__init__.pyi
locan/__main__.py
locan/_version.py
locan/configuration.py
locan/constants.py
locan/datasets.py
locan/dependencies.py
locan/locan_types.py
locan/py.typed
locan/analysis/__init__.py
locan/analysis/accumulation_analysis.py
locan/analysis/analysis_base.py
locan/analysis/blinking.py
locan/analysis/cbc.py
locan/analysis/convex_hull_expectation.py
locan/analysis/drift.py
locan/analysis/grouped_property_expectation.py
locan/analysis/local_density.py
locan/analysis/localization_precision.py
locan/analysis/localization_property.py
locan/analysis/localization_property_2d.py
locan/analysis/localization_property_correlations.py
locan/analysis/localizations_per_frame.py
locan/analysis/metadata_analysis.proto
locan/analysis/metadata_analysis_pb2.py
locan/analysis/metadata_analysis_pb2.pyi
locan/analysis/nearest_neighbor.py
locan/analysis/pair_distances.py
locan/analysis/pipeline.py
locan/analysis/position_variance_expectation.py
locan/analysis/radial_distribution.py
locan/analysis/ripley.py
locan/analysis/subpixel_bias.py
locan/analysis/uncertainty.py
locan/analysis/resources/__init__.py
locan/analysis/resources/convex_hull_expectation/__init__.py
locan/analysis/resources/convex_hull_expectation/lookup_table_area_2d.npy
locan/analysis/resources/convex_hull_expectation/lookup_table_area_3d.npy
locan/analysis/resources/convex_hull_expectation/lookup_table_peri_2d.npy
locan/analysis/resources/convex_hull_expectation/lookup_table_vol_3d.npy
locan/data/__init__.py
locan/data/images.py
locan/data/locdata.py
locan/data/locdata_utils.py
locan/data/metadata.proto
locan/data/metadata_pb2.py
locan/data/metadata_pb2.pyi
locan/data/metadata_utils.py
locan/data/metadata_v0p11_legacy.proto
locan/data/validation.py
locan/data/adapter/__init__.py
locan/data/adapter/adapter_open3d.py
locan/data/hulls/__init__.py
locan/data/hulls/alpha_shape.py
locan/data/hulls/alpha_shape_2d.py
locan/data/hulls/hull.py
locan/data/regions/__init__.py
locan-0.21.0.dist-info/licenses/LICENSE.md
locan-0.21.0.dist-info/METADATA
locan-0.21.0.dist-info/WHEEL
locan-0.21.0.dist-info/entry_points.txt
locan-0.21.0.dist-info/top_level.txt
locan-0.21.0.dist-info/RECORD
