Metadata-Version: 2.4
Name: locan
Version: 0.21.0
Summary: Analysis software for single-molecule localization microscopy
Author: Locan Developers
Maintainer: Sören Doose
License: BSD 3-Clause License
Project-URL: homepage, https://github.com/super-resolution/locan
Project-URL: documentation, https://locan.readthedocs.io/
Project-URL: repository, https://github.com/super-resolution/locan
Project-URL: issues, https://github.com/super-resolution/locan/issues
Project-URL: changelog, https://github.com/super-resolution/locan
Keywords: fluorescence,super-resolution, single-molecule localization microscopy,smlm,storm,dstorm,palm,paint
Classifier: Environment :: Console
Classifier: Development Status :: 3 - Alpha
Classifier: Intended Audience :: Education
Classifier: Intended Audience :: Science/Research
Classifier: License :: OSI Approved :: BSD License
Classifier: Programming Language :: C
Classifier: Programming Language :: Python
Classifier: Programming Language :: Python :: 3
Classifier: Programming Language :: Python :: 3.10
Classifier: Programming Language :: Python :: 3.11
Classifier: Programming Language :: Python :: 3.12
Classifier: Programming Language :: Python :: 3.13
Classifier: Operating System :: Microsoft :: Windows
Classifier: Operating System :: POSIX
Classifier: Operating System :: Unix
Classifier: Operating System :: MacOS
Classifier: Topic :: Scientific/Engineering
Classifier: Topic :: Scientific/Engineering :: Bio-Informatics
Requires-Python: >=3.9
License-File: LICENSE.md
Requires-Dist: asdf
Requires-Dist: boost-histogram
Requires-Dist: cython
Requires-Dist: fast-histogram
Requires-Dist: lazy_loader>=0.3
Requires-Dist: lmfit
Requires-Dist: matplotlib
Requires-Dist: networkx
Requires-Dist: numpy>1.20.0
Requires-Dist: pandas
Requires-Dist: protobuf>=6.31.1
Requires-Dist: qtpy!=2.3.0
Requires-Dist: ruamel.yaml
Requires-Dist: scikit-image
Requires-Dist: scikit-learn
Requires-Dist: scipy
Requires-Dist: shapely!=2.0.0,!=2.0.1
Requires-Dist: tifffile
Requires-Dist: tomli>=1.1.0; python_version < "3.11"
Requires-Dist: tqdm
Requires-Dist: typing_extensions
Provides-Extra: color
Requires-Dist: colorcet; extra == "color"
Provides-Extra: hdf5
Requires-Dist: h5py; extra == "hdf5"
Provides-Extra: http
Requires-Dist: httpx; extra == "http"
Provides-Extra: napari
Requires-Dist: napari>=0.5.3; extra == "napari"
Provides-Extra: pyqt5
Requires-Dist: PyQt5; extra == "pyqt5"
Provides-Extra: pyside2
Requires-Dist: PySide2; extra == "pyside2"
Provides-Extra: pyside6
Requires-Dist: pyside6!=6.8.0; extra == "pyside6"
Provides-Extra: register
Requires-Dist: open3d-cpu!=0.12.0; (platform_system == "Linux" and python_version < "3.13") and extra == "register"
Requires-Dist: open3d!=0.12.0; (platform_system != "Linux" and python_version < "3.13") and extra == "register"
Provides-Extra: scatter-density
Requires-Dist: mpl_scatter_density; extra == "scatter-density"
Requires-Dist: setuptools; extra == "scatter-density"
Provides-Extra: test
Requires-Dist: pytest; extra == "test"
Provides-Extra: track
Requires-Dist: trackpy; extra == "track"
Provides-Extra: all
Requires-Dist: colorcet; extra == "all"
Requires-Dist: h5py; extra == "all"
Requires-Dist: locan[http]; extra == "all"
Requires-Dist: locan[napari]; extra == "all"
Requires-Dist: locan[register]; extra == "all"
Requires-Dist: locan[scatter_density]; extra == "all"
Requires-Dist: locan[test]; extra == "all"
Requires-Dist: trackpy; extra == "all"
Provides-Extra: gpu
Requires-Dist: cupy-cuda12x; extra == "gpu"
Requires-Dist: open3d!=0.12.0; python_version < "3.13" and extra == "gpu"
Provides-Extra: test-qt
Requires-Dist: pytest; extra == "test-qt"
Requires-Dist: pytest-qt; python_version < "3.13" and extra == "test-qt"
Provides-Extra: docs
Requires-Dist: furo; extra == "docs"
Requires-Dist: ipython; extra == "docs"
Requires-Dist: myst-nb; extra == "docs"
Requires-Dist: ray[default]; python_version < "3.13" and extra == "docs"
Requires-Dist: sphinx; extra == "docs"
Requires-Dist: sphinx-autodoc-typehints; extra == "docs"
Requires-Dist: sphinx-copybutton; extra == "docs"
Provides-Extra: dev
Requires-Dist: asv; extra == "dev"
Requires-Dist: black~=25.0; extra == "dev"
Requires-Dist: build; extra == "dev"
Requires-Dist: coverage[toml]; extra == "dev"
Requires-Dist: mypy; extra == "dev"
Requires-Dist: pandas-stubs; extra == "dev"
Requires-Dist: pre-commit; extra == "dev"
Requires-Dist: ruff; extra == "dev"
Requires-Dist: twine; extra == "dev"
Requires-Dist: types-networkx; extra == "dev"
Requires-Dist: types-protobuf; extra == "dev"
Requires-Dist: types-shapely; extra == "dev"
Requires-Dist: types-tqdm; extra == "dev"
Dynamic: license-file
